{
    "name": "Java Basic",
    "level": "BASIC",
    "description": "Java — найбільш поширена мова програмування, вона не складна в освоєнні, тому підходить тим, хто вперше підійшов до вивчення програмування, а попит на Java розробників стабільно високий. На курсі ви дізнаєтеся базові принципи програмування на мові Java, а також про те, які є змінні, типи даних і багато іншого.",
    "prices": 12000 ,
    "link" : "https://ithillel.ua/courses/introduction-python",
    "lessons_count": "16 заняття"
}